{
  "title": "[EUR] 3. domaća zadaća - 2020/2021",
  "creator": "246",
  "slug": "eur-3-domaca-zadaca-20202021",
  "tags": [
    "FER",
    "Ergonomija u računarstvu",
    "Zadaće"
  ],
  "posts": {
    "187141": {
      "poster": "246",
      "content": "![](assets/2021-05-09/00006.png)\n\nzna li netko koje su to dvije teskoce? (nisu nikoje dvije izricito navedene u prethodnim pitanjima)",
      "votes": {
        "upvoters": [
          "Galke",
          "iva7740 (Mica Trofrtaljka)"
        ],
        "downvoters": []
      },
      "reactions": {
        "haha": [],
        "wtf": [],
        "tuga": []
      }
    },
    "187178": {
      "poster": "Nocna_smjena",
      "content": "![](assets/2021-05-09/00012.jpeg)\n\nZa zadacu iz Dizajna za sve. Zar nije ovo pitanje dvosmisleno? Kad se rjesavas kviz jedino ti se nudi da povecas velicinu slova ali ne i smanjit. Tek mozes smanjit velicinu slova kad si ih povecao. Tj po defaultu imas najmanja slova. I sto bi ovo iskljucivanje svijetla uopce trebalo znacit? Nesto ko visoki kontrast ili night mode mi lici.",
      "votes": {
        "upvoters": [],
        "downvoters": []
      },
      "reactions": {
        "haha": [],
        "wtf": [],
        "tuga": []
      }
    },
    "187179": {
      "poster": "Joskica",
      "content": "Evo ja sam rijesila i ova 4 pitanja na zaokruzivanje su mi tocna pa evo:\n>!![](assets/2021-05-09/00013.png)\n\n>![](assets/2021-05-09/00014.png)\n\n>![](assets/2021-05-09/00015.png)",
      "votes": {
        "upvoters": [
          "Lusy (MGJ)",
          "Nocna_smjena",
          "aerius",
          "blablajar",
          "lucylu"
        ],
        "downvoters": []
      },
      "reactions": {
        "haha": [],
        "wtf": [],
        "tuga": []
      }
    },
    "187180": {
      "poster": "Joskica",
      "content": "@Nocna_smjena#187178 ako stisnes na povecanje slova, slova se povecaju i onda ti ta ista opcija postaje smanjivanje slova",
      "votes": {
        "upvoters": [
          "Nocna_smjena"
        ],
        "downvoters": []
      },
      "reactions": {
        "haha": [],
        "wtf": [],
        "tuga": []
      }
    },
    "187181": {
      "poster": "Nocna_smjena",
      "content": "@Joskica#187180 Hvalaaa 🤗",
      "votes": {
        "upvoters": [
          "Joskica"
        ],
        "downvoters": []
      },
      "reactions": {
        "haha": [],
        "wtf": [],
        "tuga": []
      }
    },
    "187184": {
      "poster": "Nocna_smjena",
      "content": "Evo mozda nekome pomogne, zadaca iz teme Dizajn za sve\n\n![](assets/2021-05-09/00016.jpeg)\n\n![](assets/2021-05-09/00017.jpeg)",
      "votes": {
        "upvoters": [
          "aerius"
        ],
        "downvoters": []
      },
      "reactions": {
        "haha": [],
        "wtf": [],
        "tuga": []
      }
    },
    "187185": {
      "poster": "Nocna_smjena",
      "content": "@246#187141 Ja sam imao drugacije pitanje tak da nazalost nemrem helpat a ni neznam na sta oni misle ovdje 😢",
      "votes": {
        "upvoters": [],
        "downvoters": []
      },
      "reactions": {
        "haha": [],
        "wtf": [],
        "tuga": []
      }
    },
    "187247": {
      "poster": "Daho_Cro",
      "content": "![](assets/2021-05-09/00031.png)\n\nMalo drugačiji ponuđeni odgovori na pitanje koje je kolega već stavio pa evo možda će nekome pomoći.",
      "votes": {
        "upvoters": [
          "Lusy (MGJ)",
          "Nocna_smjena"
        ],
        "downvoters": []
      },
      "reactions": {
        "haha": [],
        "wtf": [],
        "tuga": []
      }
    }
  }
}